{
  "_class": "group",
  "booleanOperation": -1,
  "clippingMaskMode": 0,
  "do_objectID": "AF9DB6F5-8A44-4A52-B936-6009DB90DABA",
  "exportOptions": {
    "_class": "exportOptions",
    "do_objectID": "C75DC54A-76B1-470F-BA6E-B1C41282BA9A",
    "exportFormats": [
    ],
    "includedLayerIds": [
    ],
    "layerOptions": 0,
    "shouldTrim": false
  },
  "frame": {
    "_class": "rect",
    "constrainProportions": false,
    "do_objectID": "1FE2CD27-0A29-4532-9C88-74B96CE59932",
    "height": 24,
    "width": 86,
    "x": 8,
    "y": 35
  },
  "groupLayout": {
    "_class": "MSImmutableFreeformGroupLayout",
    "do_objectID": "EB5DF47D-CBDD-418E-B5E8-68DB4631C3D4"
  },
  "hasClickThrough": false,
  "hasClippingMask": false,
  "isFixedToViewport": false,
  "isFlippedHorizontal": false,
  "isFlippedVertical": false,
  "isLocked": false,
  "isVisible": true,
  "layerListExpandedType": 0,
  "layers": [
    {
      "class": "symbolInstance",
      "id": "48487088-6D0A-4F98-BF04-09BAE4E1A1A4"
    },
    {
      "class": "text",
      "id": "8473A49F-DF21-4EF2-B2D8-EEB206729F8F"
    }
  ],
  "name": "Group 3",
  "nameIsFixed": false,
  "resizingConstraint": 63,
  "resizingType": 0,
  "rotation": 0,
  "shouldBreakMaskChain": false,
  "style": {
    "_class": "style",
    "do_objectID": "DDD84C75-6A83-47A6-B212-2AFFD2FF65AF",
    "endMarkerType": 0,
    "miterLimit": 10,
    "startMarkerType": 0,
    "windingRule": 1
  }
}