{
  "_class": "shapePath",
  "booleanOperation": -1,
  "clippingMaskMode": 0,
  "do_objectID": "FEB1DE8B-2150-4D1F-B41B-8A801CDA85C6",
  "edited": true,
  "exportOptions": {
    "_class": "exportOptions",
    "do_objectID": "9897E94B-AAB1-4175-98E1-605E377C84D7",
    "exportFormats": [
    ],
    "includedLayerIds": [
    ],
    "layerOptions": 0,
    "shouldTrim": false
  },
  "frame": {
    "_class": "rect",
    "constrainProportions": true,
    "do_objectID": "26D1BCC6-8B5E-44CC-968F-CE3895F710DA",
    "height": 49.07692307692296,
    "width": 40,
    "x": 0,
    "y": 0
  },
  "hasClippingMask": false,
  "isClosed": true,
  "isFixedToViewport": false,
  "isFlippedHorizontal": false,
  "isFlippedVertical": false,
  "isLocked": false,
  "isVisible": true,
  "layerListExpandedType": 0,
  "maintainScrollPosition": false,
  "name": "value bg",
  "nameIsFixed": true,
  "pointRadiusBehaviour": 0,
  "points": [
    {
      "_class": "curvePoint",
      "cornerRadius": 0,
      "curveFrom": "{0.77692307692307694, 0}",
      "curveMode": 4,
      "curveTo": "{0.49999999999999994, 0}",
      "hasCurveFrom": true,
      "hasCurveTo": false,
      "point": "{0.49999999999999994, 0}"
    },
    {
      "_class": "curvePoint",
      "cornerRadius": 0,
      "curveFrom": "{1, 0.52978056426332532}",
      "curveMode": 3,
      "curveTo": "{1, 0.18495297805642608}",
      "hasCurveFrom": true,
      "hasCurveTo": true,
      "point": "{1, 0.41379310344827652}"
    },
    {
      "_class": "curvePoint",
      "cornerRadius": 0,
      "curveFrom": "{0.71923076923076923, 0.81818181818181912}",
      "curveMode": 4,
      "curveTo": "{0.92307692307692313, 0.65203761755486089}",
      "hasCurveFrom": false,
      "hasCurveTo": true,
      "point": "{0.71923076923076923, 0.81818181818181912}"
    },
    {
      "_class": "curvePoint",
      "cornerRadius": 0,
      "curveFrom": "{0.49999999999999994, 1}",
      "curveMode": 1,
      "curveTo": "{0.49999999999999994, 1}",
      "hasCurveFrom": false,
      "hasCurveTo": false,
      "point": "{0.49999999999999994, 1}"
    },
    {
      "_class": "curvePoint",
      "cornerRadius": 0,
      "curveFrom": "{0.076923076923076927, 0.6489028213166157}",
      "curveMode": 4,
      "curveTo": "{0.27692307692307688, 0.81818181818181912}",
      "hasCurveFrom": true,
      "hasCurveTo": false,
      "point": "{0.27692307692307688, 0.81818181818181912}"
    },
    {
      "_class": "curvePoint",
      "cornerRadius": 0,
      "curveFrom": "{-1.3664283380001927e-16, 0.18495297805642785}",
      "curveMode": 3,
      "curveTo": "{0, 0.52664576802508001}",
      "hasCurveFrom": true,
      "hasCurveTo": true,
      "point": "{0, 0.41379310344827652}"
    },
    {
      "_class": "curvePoint",
      "cornerRadius": 0,
      "curveFrom": "{0.49999999999999994, 0}",
      "curveMode": 4,
      "curveTo": "{0.22307692307692298, 0}",
      "hasCurveFrom": false,
      "hasCurveTo": true,
      "point": "{0.49999999999999994, 0}"
    }
  ],
  "resizingConstraint": 45,
  "resizingType": 0,
  "rotation": 0,
  "shouldBreakMaskChain": false,
  "style": {
    "_class": "style",
    "blur": {
      "_class": "blur",
      "center": "{0.5, 0.5}",
      "isEnabled": false,
      "motionAngle": 0,
      "radius": 10,
      "saturation": 1,
      "type": 0
    },
    "borderOptions": {
      "_class": "borderOptions",
      "dashPattern": [
      ],
      "isEnabled": true,
      "lineCapStyle": 0,
      "lineJoinStyle": 0
    },
    "borders": [
    ],
    "colorControls": {
      "_class": "colorControls",
      "brightness": 0,
      "contrast": 1,
      "hue": 0,
      "isEnabled": true,
      "saturation": 1
    },
    "contextSettings": {
      "_class": "graphicsContextSettings",
      "blendMode": 0,
      "opacity": 1
    },
    "do_objectID": "0EA6AD8E-A44F-454F-8DA2-DD2BBABEA160",
    "endMarkerType": 0,
    "fills": [
      {
        "_class": "fill",
        "color": {
          "_class": "color",
          "alpha": 1,
          "blue": 0.8549019607843137,
          "green": 0.5372549019607843,
          "red": 0.4470588235294117
        },
        "contextSettings": {
          "_class": "graphicsContextSettings",
          "blendMode": 0,
          "opacity": 1
        },
        "do_objectID": "3AF3E26F-946C-4AEC-B5CF-34F65CADBA33",
        "fillType": 0,
        "gradient": {
          "_class": "gradient",
          "elipseLength": 0,
          "from": "{0.5, 0}",
          "gradientType": 0,
          "stops": [
            {
              "_class": "gradientStop",
              "color": {
                "_class": "color",
                "alpha": 1,
                "blue": 1,
                "green": 1,
                "red": 1
              },
              "position": 0
            },
            {
              "_class": "gradientStop",
              "color": {
                "_class": "color",
                "alpha": 1,
                "blue": 0,
                "green": 0,
                "red": 0
              },
              "position": 1
            }
          ],
          "to": "{0.5, 1}"
        },
        "isEnabled": true,
        "noiseIndex": 0,
        "noiseIntensity": 0,
        "patternFillType": 0,
        "patternTileScale": 1
      }
    ],
    "innerShadows": [
    ],
    "miterLimit": 10,
    "shadows": [
    ],
    "startMarkerType": 0,
    "windingRule": 1
  },
  "userInfo": {
    "com.animaapp.stc-sketch-plugin": {
      "kModelPropertiesKey": {
        "constraints": {
          "aspectRatio": {
            "constant": 49.07692,
            "enabled": 1,
            "modelID": "constraint_dc732521-7221-49e0-9ad9-a3953864df93",
            "model_class": "ADModelConstraint",
            "model_version": 0,
            "multiplier": 40
          },
          "automatic": 1,
          "modelID": "viewConstraints_eb404c93-b990-4805-bc78-94841ef1b8d2",
          "model_class": "ADModelViewConstraints",
          "model_version": 0,
          "scaleFactor": 1
        }
      }
    }
  }
}