{
  "_class": "group",
  "booleanOperation": -1,
  "clippingMaskMode": 0,
  "do_objectID": "289D9815-0988-4FEB-8A29-0E22D443601D",
  "exportOptions": {
    "_class": "exportOptions",
    "do_objectID": "187BBA46-A2EA-408E-BE38-323BB9D85872",
    "exportFormats": [
      {
        "_class": "exportFormat",
        "absoluteSize": 0,
        "fileFormat": "png",
        "name": "",
        "namingScheme": 0,
        "scale": 1,
        "visibleScaleType": 0
      }
    ],
    "includedLayerIds": [
    ],
    "layerOptions": 0,
    "shouldTrim": false
  },
  "frame": {
    "_class": "rect",
    "constrainProportions": false,
    "do_objectID": "75D38D2E-3E87-4D07-8A62-1EF0FEEB785E",
    "height": 821,
    "width": 1440,
    "x": 0,
    "y": 0
  },
  "groupLayout": {
    "_class": "MSImmutableFreeformGroupLayout",
    "do_objectID": "5AD361D4-DA57-4934-BFE5-E1CD94F4B874"
  },
  "hasClickThrough": false,
  "hasClippingMask": false,
  "isFixedToViewport": false,
  "isFlippedHorizontal": false,
  "isFlippedVertical": false,
  "isLocked": false,
  "isVisible": true,
  "layerListExpandedType": 0,
  "layers": [
    {
      "class": "bitmap",
      "id": "44672D5E-DC79-4A4F-BD16-6E187533AFAE"
    },
    {
      "class": "rectangle",
      "id": "7EBFAF45-A1C0-4F8E-A10B-4772C2785881"
    }
  ],
  "name": "Group",
  "nameIsFixed": false,
  "resizingConstraint": 63,
  "resizingType": 0,
  "rotation": 0,
  "shouldBreakMaskChain": false,
  "style": {
    "_class": "style",
    "do_objectID": "EFD49180-8B6E-4580-B391-4F039112D0E4",
    "endMarkerType": 0,
    "miterLimit": 10,
    "startMarkerType": 0,
    "windingRule": 1
  }
}