{
  "_class": "symbolInstance",
  "booleanOperation": -1,
  "clippingMaskMode": 0,
  "do_objectID": "71827D9A-896F-4273-9E38-04E607E3E2A1",
  "exportOptions": {
    "_class": "exportOptions",
    "do_objectID": "5D78D03C-9398-4AA3-AE28-00D41344C6C1",
    "exportFormats": [
    ],
    "includedLayerIds": [
    ],
    "layerOptions": 0,
    "shouldTrim": false
  },
  "frame": {
    "_class": "rect",
    "constrainProportions": false,
    "do_objectID": "C9BD76B4-3569-4591-A964-1542D08E6DA2",
    "height": 51,
    "width": 102,
    "x": 40,
    "y": 23
  },
  "hasClippingMask": false,
  "horizontalSpacing": 0,
  "isFixedToViewport": false,
  "isFlippedHorizontal": false,
  "isFlippedVertical": false,
  "isLocked": false,
  "isVisible": true,
  "layerListExpandedType": 0,
  "name": "Button Outline",
  "nameIsFixed": false,
  "overrideValues": [
    {
      "_class": "overrideValue",
      "do_objectID": "B3409C49-8A95-4548-9DC4-6F7606FE222E",
      "overrideName": "E2F7AA52-3CD2-473D-9616-833F1D297F41_stringValue",
      "value": "SIGN UP"
    }
  ],
  "resizingConstraint": 63,
  "resizingType": 0,
  "rotation": 0,
  "scale": 1,
  "shouldBreakMaskChain": false,
  "style": {
    "_class": "style",
    "do_objectID": "E08AABE8-217D-44D8-B539-5A662FA58F7B",
    "endMarkerType": 0,
    "miterLimit": 10,
    "startMarkerType": 0,
    "windingRule": 1
  },
  "symbolID": "400BF038-7FC5-4751-8E14-F551772328B1",
  "userInfo": {
    "com.animaapp.stc-sketch-plugin": {
      "kModelPropertiesKey": {
        "size.update": 1560293110.649464
      }
    }
  },
  "verticalSpacing": 0
}