{
  "_class": "symbolInstance",
  "booleanOperation": -1,
  "clippingMaskMode": 0,
  "do_objectID": "45FBD03B-CE26-4E87-A5CA-68156605171C",
  "exportOptions": {
    "_class": "exportOptions",
    "do_objectID": "4884015A-5DAC-4545-B5AA-ED77B3A282AA",
    "exportFormats": [
    ],
    "includedLayerIds": [
    ],
    "layerOptions": 0,
    "shouldTrim": false
  },
  "frame": {
    "_class": "rect",
    "constrainProportions": false,
    "do_objectID": "A8DBFFE3-4E99-43C0-83DB-D42AEB0CBEA7",
    "height": 29,
    "width": 90,
    "x": 152,
    "y": 74
  },
  "hasClippingMask": false,
  "horizontalSpacing": 0,
  "isFixedToViewport": false,
  "isFlippedHorizontal": false,
  "isFlippedVertical": false,
  "isLocked": false,
  "isVisible": true,
  "layerListExpandedType": 0,
  "name": "Genre Filter Button Copy 3",
  "nameIsFixed": false,
  "overrideValues": [
    {
      "_class": "overrideValue",
      "do_objectID": "8E4CF44F-2EAF-4DEF-B2FE-62FBE93DD6DF",
      "overrideName": "0380F3F7-FCF2-43E3-9BAB-DF1CA0EA7717_stringValue",
      "value": "Mystery"
    }
  ],
  "resizingConstraint": 63,
  "resizingType": 0,
  "rotation": 0,
  "scale": 1,
  "shouldBreakMaskChain": false,
  "style": {
    "_class": "style",
    "do_objectID": "047AE72A-F48F-47C6-B5EF-8AF3284CF6DC",
    "endMarkerType": 0,
    "miterLimit": 10,
    "startMarkerType": 0,
    "windingRule": 1
  },
  "symbolID": "F6453712-43D9-4238-A17E-88424E9562A6",
  "userInfo": {
    "com.animaapp.stc-sketch-plugin": {
      "kModelPropertiesKey": {
        "size.update": 1560293110.753975
      }
    }
  },
  "verticalSpacing": 0
}