{
  "_class": "artboard",
  "backgroundColor": {
    "_class": "color",
    "alpha": 1,
    "blue": 0.9803921568627451,
    "do_objectID": "3C8CC98D-2DBA-45B1-9162-86B369A028F3",
    "green": 0.9803921568627451,
    "red": 0.9803921568627451
  },
  "booleanOperation": -1,
  "clippingMaskMode": 0,
  "do_objectID": "1D7E7E76-40CE-4F68-9B18-3395BE37DE09",
  "exportOptions": {
    "_class": "exportOptions",
    "do_objectID": "D63C6924-6D15-4C28-AF6A-15E720A8A650",
    "exportFormats": [
      {
        "_class": "exportFormat",
        "absoluteSize": 0,
        "fileFormat": "png",
        "name": "",
        "namingScheme": 0,
        "scale": 2,
        "visibleScaleType": 0
      }
    ],
    "includedLayerIds": [
    ],
    "layerOptions": 0,
    "shouldTrim": false
  },
  "frame": {
    "_class": "rect",
    "constrainProportions": false,
    "do_objectID": "3902D493-F6B5-4687-9BF0-ED178E047D8B",
    "height": 1024,
    "width": 320,
    "x": 1100,
    "y": 5219
  },
  "groupLayout": {
    "_class": "MSImmutableFreeformGroupLayout",
    "do_objectID": "9568DB18-EABC-4214-90CB-B0F184DD627F"
  },
  "hasBackgroundColor": true,
  "hasClickThrough": true,
  "hasClippingMask": false,
  "horizontalRulerData": {
    "_class": "rulerData",
    "base": 0,
    "do_objectID": "02586D48-259D-4859-8A61-A3525BCF52F9",
    "guides": [
    ]
  },
  "includeBackgroundColorInExport": true,
  "includeInCloudUpload": true,
  "isFixedToViewport": false,
  "isFlippedHorizontal": false,
  "isFlippedVertical": false,
  "isFlowHome": false,
  "isLocked": false,
  "isVisible": true,
  "layerListExpandedType": 2,
  "layers": [
    {
      "class": "symbolInstance",
      "id": "1F9BD47A-BECE-4AAB-AAFD-22DF6BF44551"
    },
    {
      "class": "symbolInstance",
      "id": "E924B68A-4AF3-4317-90F1-6284AF11A6D2"
    }
  ],
  "maintainScrollPosition": false,
  "name": "Mobile / Search / Start / KotS",
  "nameIsFixed": true,
  "presetDictionary": {
    "allowResizedMatching": 0,
    "height": 1024,
    "name": "Mobile",
    "offersLandscapeVariant": 1,
    "width": 320
  },
  "resizesContent": true,
  "resizingConstraint": 63,
  "resizingType": 0,
  "rotation": 0,
  "shouldBreakMaskChain": true,
  "style": {
    "_class": "style",
    "blur": {
      "_class": "blur",
      "center": "{0.5, 0.5}",
      "isEnabled": false,
      "motionAngle": 0,
      "radius": 10,
      "saturation": 1,
      "type": 0
    },
    "borderOptions": {
      "_class": "borderOptions",
      "dashPattern": [
      ],
      "isEnabled": true,
      "lineCapStyle": 0,
      "lineJoinStyle": 0
    },
    "borders": [
    ],
    "colorControls": {
      "_class": "colorControls",
      "brightness": 0,
      "contrast": 1,
      "hue": 0,
      "isEnabled": true,
      "saturation": 1
    },
    "contextSettings": {
      "_class": "graphicsContextSettings",
      "blendMode": 0,
      "opacity": 1
    },
    "do_objectID": "E814051F-3CDE-4CE5-9AAA-CFC0C5A3A2D8",
    "endMarkerType": 0,
    "fills": [
    ],
    "innerShadows": [
    ],
    "miterLimit": 10,
    "shadows": [
    ],
    "startMarkerType": 0,
    "windingRule": 1
  },
  "verticalRulerData": {
    "_class": "rulerData",
    "base": 0,
    "do_objectID": "893E5535-729D-43C3-8AE4-903DCCEF435B",
    "guides": [
    ]
  }
}