{
  "_class": "group",
  "booleanOperation": -1,
  "clippingMaskMode": 0,
  "do_objectID": "8F415FE6-765D-4439-AD63-E313001900C5",
  "exportOptions": {
    "_class": "exportOptions",
    "do_objectID": "0FFACA87-C4C5-4CDC-B4D5-FF0840307646",
    "exportFormats": [
    ],
    "includedLayerIds": [
    ],
    "layerOptions": 0,
    "shouldTrim": false
  },
  "frame": {
    "_class": "rect",
    "constrainProportions": false,
    "do_objectID": "FEA93181-E463-431E-BC4C-A77BBC14FA2F",
    "height": 15,
    "width": 109,
    "x": 21,
    "y": 342
  },
  "groupLayout": {
    "_class": "MSImmutableFreeformGroupLayout",
    "do_objectID": "869CEDDE-7041-4E56-BBDE-936C8EA45D1E"
  },
  "hasClickThrough": false,
  "hasClippingMask": false,
  "isFixedToViewport": false,
  "isFlippedHorizontal": false,
  "isFlippedVertical": false,
  "isLocked": false,
  "isVisible": true,
  "layerListExpandedType": 2,
  "layers": [
    {
      "class": "text",
      "id": "F1EBC64D-4B5E-40E7-AE21-A1A94CB90F2A"
    }
  ],
  "name": "Read Speed",
  "nameIsFixed": true,
  "resizingConstraint": 63,
  "resizingType": 0,
  "rotation": 0,
  "shouldBreakMaskChain": false,
  "style": {
    "_class": "style",
    "do_objectID": "3553F812-8CD5-4556-BC6F-88BFE1319EA6",
    "endMarkerType": 0,
    "miterLimit": 10,
    "startMarkerType": 0,
    "windingRule": 1
  }
}