{
  "_class": "symbolInstance",
  "booleanOperation": -1,
  "clippingMaskMode": 0,
  "do_objectID": "18582EF9-4220-410F-A2EB-317D87E3F7E4",
  "exportOptions": {
    "_class": "exportOptions",
    "do_objectID": "016B7CA8-7893-4F14-BB20-4EA04ABB91CB",
    "exportFormats": [
    ],
    "includedLayerIds": [
    ],
    "layerOptions": 0,
    "shouldTrim": false
  },
  "frame": {
    "_class": "rect",
    "constrainProportions": false,
    "do_objectID": "8A3692C4-F6B3-4819-9B21-02E64DC0324F",
    "height": 27,
    "width": 97,
    "x": 0,
    "y": 43
  },
  "hasClippingMask": false,
  "horizontalSpacing": 0,
  "isFixedToViewport": false,
  "isFlippedHorizontal": false,
  "isFlippedVertical": false,
  "isLocked": false,
  "isVisible": true,
  "layerListExpandedType": 0,
  "name": "Buttons / Genre Filter Unselected Copy 2",
  "nameIsFixed": false,
  "overrideValues": [
    {
      "_class": "overrideValue",
      "do_objectID": "59D126D9-4B40-4A36-8BA8-3A92A48030C8",
      "overrideName": "E0AE3C4E-C6A9-4A50-84A5-37EEB9908E0F_stringValue",
      "value": "Classics"
    }
  ],
  "resizingConstraint": 63,
  "resizingType": 0,
  "rotation": 0,
  "scale": 1,
  "shouldBreakMaskChain": false,
  "style": {
    "_class": "style",
    "do_objectID": "EED20F91-4F6A-4A0F-B3C6-FBFF1815B28D",
    "endMarkerType": 0,
    "miterLimit": 10,
    "startMarkerType": 0,
    "windingRule": 1
  },
  "symbolID": "284FE7A0-0ED9-45E1-839C-FFE6C9418D26",
  "userInfo": {
    "com.animaapp.stc-sketch-plugin": {
      "kModelPropertiesKey": {
        "size.update": 1561495353.418624
      }
    }
  },
  "verticalSpacing": 0
}