{
  "_class": "artboard",
  "backgroundColor": {
    "_class": "color",
    "alpha": 1,
    "blue": 1,
    "do_objectID": "F29C2C78-98A5-43CB-852D-6ADFD469DB77",
    "green": 1,
    "red": 1
  },
  "booleanOperation": -1,
  "clippingMaskMode": 0,
  "do_objectID": "96FCD0F9-0714-4E68-AAA4-113395794F7A",
  "exportOptions": {
    "_class": "exportOptions",
    "do_objectID": "B7340796-C8F7-4953-8EBA-5DC9143FC3EB",
    "exportFormats": [
    ],
    "includedLayerIds": [
    ],
    "layerOptions": 0,
    "shouldTrim": false
  },
  "frame": {
    "_class": "rect",
    "constrainProportions": false,
    "do_objectID": "69D6CAFE-B140-41D9-B4A1-D3B79108CC9F",
    "height": 1024,
    "width": 320,
    "x": 260,
    "y": 2771
  },
  "groupLayout": {
    "_class": "MSImmutableFreeformGroupLayout",
    "do_objectID": "8F02A542-39B4-4808-BA16-A3E289FDABA1"
  },
  "hasBackgroundColor": false,
  "hasClickThrough": true,
  "hasClippingMask": false,
  "horizontalRulerData": {
    "_class": "rulerData",
    "base": 0,
    "do_objectID": "82E97C63-9EB0-4859-8068-F5FC50953AC0",
    "guides": [
    ]
  },
  "includeBackgroundColorInExport": true,
  "includeInCloudUpload": true,
  "isFixedToViewport": false,
  "isFlippedHorizontal": false,
  "isFlippedVertical": false,
  "isFlowHome": false,
  "isLocked": false,
  "isVisible": true,
  "layerListExpandedType": 2,
  "layers": [
    {
      "class": "symbolInstance",
      "id": "933E55DF-7B5D-4A86-A269-02CD74208490"
    },
    {
      "class": "group",
      "id": "A5AABEBF-2AC0-47B3-907C-988DE068B240"
    },
    {
      "class": "symbolInstance",
      "id": "6D96AE24-B80D-40C3-8360-18FFB856B9DA"
    },
    {
      "class": "group",
      "id": "C466597A-5994-4D38-978E-8BA73C17C575"
    },
    {
      "class": "group",
      "id": "FCACBF49-59CE-4EBA-B581-F5C4DABFE254"
    },
    {
      "class": "symbolInstance",
      "id": "9919F1C6-0601-460E-BF56-B74EA2A4202B"
    },
    {
      "class": "group",
      "id": "1D57FD5F-B2C6-433C-851D-07B4EC443151"
    },
    {
      "class": "group",
      "id": "BFC79B42-B3EC-4442-9574-2EBE3376C102"
    },
    {
      "class": "symbolInstance",
      "id": "F6F02F77-EFB2-447C-A02A-EB7F6B0AF980"
    },
    {
      "class": "rectangle",
      "id": "977FAC57-320E-465B-9BFD-4E2F0BEC1D8C"
    },
    {
      "class": "group",
      "id": "01A9BF8D-BD40-4E4B-8A21-4C27E7656AB4"
    },
    {
      "class": "rectangle",
      "id": "82DB387C-B282-4EBC-B062-E5E357A81DA5"
    },
    {
      "class": "rectangle",
      "id": "C138E4B7-B048-417F-94F6-2440AF2D3ED1"
    },
    {
      "class": "rectangle",
      "id": "7B26EF2F-04DF-484B-8563-6D018906DA9E"
    },
    {
      "class": "symbolInstance",
      "id": "63CBFC6F-BC60-45AF-9C27-A69A059CDA34"
    }
  ],
  "name": "Mobile / Group Page / Not Member / Shelf",
  "nameIsFixed": true,
  "presetDictionary": {
    "allowResizedMatching": 0,
    "height": 1024,
    "name": "Mobile",
    "offersLandscapeVariant": 1,
    "width": 320
  },
  "resizesContent": false,
  "resizingConstraint": 63,
  "resizingType": 0,
  "rotation": 0,
  "shouldBreakMaskChain": true,
  "style": {
    "_class": "style",
    "do_objectID": "59E8FAD6-F432-4181-BC22-9A8ADB62DCA6",
    "endMarkerType": 0,
    "miterLimit": 10,
    "startMarkerType": 0,
    "windingRule": 1
  },
  "verticalRulerData": {
    "_class": "rulerData",
    "base": 0,
    "do_objectID": "9A25A674-D693-4C40-9290-8B2A8373EBE4",
    "guides": [
    ]
  }
}